HISTORY.txt
README.txt
setup.py
agsci/__init__.py
agsci.blognewsletter.egg-info/PKG-INFO
agsci.blognewsletter.egg-info/SOURCES.txt
agsci.blognewsletter.egg-info/dependency_links.txt
agsci.blognewsletter.egg-info/entry_points.txt
agsci.blognewsletter.egg-info/namespace_packages.txt
agsci.blognewsletter.egg-info/not-zip-safe
agsci.blognewsletter.egg-info/requires.txt
agsci.blognewsletter.egg-info/top_level.txt
agsci/blognewsletter/__init__.py
agsci/blognewsletter/config.py
agsci/blognewsletter/configure.zcml
agsci/blognewsletter/events.py
agsci/blognewsletter/extender.py
agsci/blognewsletter/interfaces.py
agsci/blognewsletter/patch.py
agsci/blognewsletter/version.txt
agsci/blognewsletter/browser/__init__.py
agsci/blognewsletter/browser/configure.zcml
agsci/blognewsletter/browser/interfaces.py
agsci/blognewsletter/browser/viewlets.py
agsci/blognewsletter/browser/views.py
agsci/blognewsletter/browser/templates/newsletter_print.pt
agsci/blognewsletter/browser/templates/newsletter_view.pt
agsci/blognewsletter/browser/templates/tags_view.pt
agsci/blognewsletter/browser/templates/tags_viewlet.pt
agsci/blognewsletter/content/Blog.py
agsci/blognewsletter/content/Newsletter.py
agsci/blognewsletter/content/__init__.py
agsci/blognewsletter/content/configure.zcml
agsci/blognewsletter/content/interfaces.py
agsci/blognewsletter/portlet/__init__.py
agsci/blognewsletter/portlet/configure.zcml
agsci/blognewsletter/portlet/tags.py
agsci/blognewsletter/portlet/templates/tags.pt
agsci/blognewsletter/profiles/default/browserlayer.xml
agsci/blognewsletter/profiles/default/catalog.xml
agsci/blognewsletter/profiles/default/factorytool.xml
agsci/blognewsletter/profiles/default/import_steps.xml
agsci/blognewsletter/profiles/default/metadata.xml
agsci/blognewsletter/profiles/default/portlets.xml
agsci/blognewsletter/profiles/default/propertiestool.xml
agsci/blognewsletter/profiles/default/rolemap.xml
agsci/blognewsletter/profiles/default/skins.xml
agsci/blognewsletter/profiles/default/types.xml
agsci/blognewsletter/profiles/default/viewlets.xml
agsci/blognewsletter/profiles/default/types/Blog.xml
agsci/blognewsletter/profiles/default/types/Newsletter.xml
agsci/blognewsletter/skins/blognewsletter/blog.png
agsci/blognewsletter/skins/blognewsletter/blog.png.metadata
agsci/blognewsletter/skins/blognewsletter/newsletter_full_view_item.pt
