Metadata-Version: 1.0
Name: agsci.blognewsletter
Version: 0.4
Summary: Plone blog/newsletter package based on the PSU AgSci products.
Home-page: http://agsci.psu.edu/
Author: Tim Simkins, College of Agricultural Sciences, Penn State University
Author-email: trs22@psu.edu
License: GPL
Platform: UNKNOWN
Classifier: Framework :: Plone
Classifier: Programming Language :: Python
Classifier: Topic :: Software Development :: Libraries :: Python Modules
Classifier: Development Status :: 2 - Pre-Alpha
